tkjsonpath/__init__.py
tkjsonpath/jsonpath.py
jsonpath_thiliapr-1.0.1.dist-info/METADATA
jsonpath_thiliapr-1.0.1.dist-info/WHEEL
jsonpath_thiliapr-1.0.1.dist-info/licenses/LICENSE
jsonpath_thiliapr-1.0.1.dist-info/RECORD
