Metadata-Version: 2.3
Name: jsonpath-thiliapr
Version: 1.0.1
Summary: A simple JSONPath parser.
Project-URL: Homepage, https://github.com/thiliapr/tkjsonpath
Project-URL: Issues, https://github.com/thiliapr/tkjsonpath/issues
Author: thiliapr
License-File: LICENSE
Classifier: License :: OSI Approved :: GNU General Public License v3 or later (GPLv3+)
Classifier: Operating System :: OS Independent
Classifier: Programming Language :: Python :: 3
Requires-Python: >=3.6
